pg_bulk_loader/__init__.py
pg_bulk_loader/batch/__init__.py
pg_bulk_loader/batch/batch_insert.py
pg_bulk_loader/batch/batch_insert_wrapper.py
pg_bulk_loader/batch/fast_load_hack.py
pg_bulk_loader/batch/pg_connection_detail.py
pg_bulk_loader/utils/__init__.py
pg_bulk_loader/utils/constants.py
pg_bulk_loader/utils/dataframe_utils.py
pg_bulk_loader/utils/time_it_decorator.py
pg_bulk_loader-2.0.0.dist-info/LICENSE
pg_bulk_loader-2.0.0.dist-info/METADATA
pg_bulk_loader-2.0.0.dist-info/WHEEL
pg_bulk_loader-2.0.0.dist-info/top_level.txt
pg_bulk_loader-2.0.0.dist-info/RECORD
