Metadata-Version: 2.1
Name: pg_bulk_loader
Version: 2.0.0
Summary: A utility package to do bulk insertion faster from pandas dataframe to postgres table.
Author-email: Aditya Jaroli <adityajaroli@gmail.com>
Project-URL: Homepage, https://github.com/adityajaroli/pg-bulk-loader.git
Project-URL: Issues, https://github.com/adityajaroli/pg-bulk-loader/issues
Classifier: Programming Language :: Python :: 3.9
Classifier: Programming Language :: Python :: 3.10
Classifier: Programming Language :: Python :: 3.11
Classifier: License :: OSI Approved :: Apache Software License
Requires-Python: >=3.9
License-File: LICENSE
Requires-Dist: pandas
Requires-Dist: psycopg[binary]
Requires-Dist: asyncio
Requires-Dist: psycopg-pool
Requires-Dist: retry
